toolboxkit/maths/__init__.py
toolboxkit/maths/addition.py
toolboxkit-1.0.2.dist-info/LICENSE
toolboxkit-1.0.2.dist-info/METADATA
toolboxkit-1.0.2.dist-info/WHEEL
toolboxkit-1.0.2.dist-info/top_level.txt
toolboxkit-1.0.2.dist-info/RECORD
