Metadata-Version: 2.2
Name: toolboxkit
Version: 1.0.2
Summary: A toolbox kit package with useful functions for Python projects.
Author: Steve Lévesque
License: MIT License
Project-URL: Homepage, https://github.com/steve-levesque/toolboxkit-python
Project-URL: Issues, https://github.com/steve-levesque/toolboxkit-python/issues
Classifier: Programming Language :: Python :: 3
Classifier: Operating System :: OS Independent
Requires-Python: >=3.8
License-File: LICENSE
